flowmatching_bdt/__init__.py
flowmatching_bdt/flow_bdt.py
flowmatching_bdt/flow_matcher.py
flowmatching_bdt/test/__init__.py
flowmatching_bdt/test/test_model.py
flowmatching_bdt-0.2.0.dist-info/LICENSE
flowmatching_bdt-0.2.0.dist-info/METADATA
flowmatching_bdt-0.2.0.dist-info/WHEEL
flowmatching_bdt-0.2.0.dist-info/top_level.txt
flowmatching_bdt-0.2.0.dist-info/RECORD
