Metadata-Version: 2.1
Name: flowmatching-bdt
Version: 0.2.0
Summary: Flow Matching with BDTs
Home-page: https://github.com/radiradev/flowmatching-bdt
Author: Radi Radev
Author-email: radi.radev.uk@gmail.com
License: MIT
Keywords: artificial intelligence,flow matching,xgboost
Classifier: Development Status :: 4 - Beta
Classifier: Intended Audience :: Developers
Classifier: Topic :: Scientific/Engineering :: Artificial Intelligence
Classifier: License :: OSI Approved :: MIT License
Classifier: Programming Language :: Python :: 3.11
License-File: LICENSE
Requires-Dist: xgboost >=2.0.0
Requires-Dist: scikit-learn >=1.3
Requires-Dist: tqdm >=4.6
Requires-Dist: tqdm-joblib >=0.0.3
